asr_bias_builder/__init__.py
asr_bias_builder/__version__.py
asr_bias_builder/cli.py
asr_bias_builder/config.py
asr_bias_builder/pipeline.py
asr_bias_builder/artifacts/__init__.py
asr_bias_builder/artifacts/google_stt.py
asr_bias_builder/artifacts/validators.py
asr_bias_builder/artifacts/whisper.py
asr_bias_builder/extraction/__init__.py
asr_bias_builder/extraction/ocr.py
asr_bias_builder/extraction/pdf.py
asr_bias_builder/extraction/pptx.py
asr_bias_builder/extraction/sections.py
asr_bias_builder/llm/__init__.py
asr_bias_builder/llm/claude.py
asr_bias_builder/llm/parser.py
asr_bias_builder/llm/prompts/instructions.md
asr_bias_builder/llm/prompts/schema.md
asr_bias_builder/mining/__init__.py
asr_bias_builder/mining/filters.py
asr_bias_builder/mining/seeds.py
asr_bias_builder/reporting/__init__.py
asr_bias_builder/reporting/csv_export.py
asr_bias_builder/reporting/summary.py
asr_bias_builder/utils/__init__.py
asr_bias_builder/utils/logging.py
asr_bias_builder/utils/telemetry.py
asr_bias_builder/utils/validation.py
asr_bias_builder/verification/__init__.py
asr_bias_builder/verification/deduplicator.py
asr_bias_builder/verification/matcher.py
asr_bias_builder/verification/scorer.py
asr_bias_builder-0.1.1.dist-info/licenses/LICENSE
examples/integration/google_stt_example.py
examples/integration/whisper_example.py
scripts/batch_process.py
scripts/benchmark.py
scripts/merge_aliases.py
tests/__init__.py
tests/conftest.py
tests/test_artifacts.py
tests/test_extraction.py
tests/test_integration.py
tests/test_mining.py
tests/test_verification.py
asr_bias_builder-0.1.1.dist-info/METADATA
asr_bias_builder-0.1.1.dist-info/WHEEL
asr_bias_builder-0.1.1.dist-info/entry_points.txt
asr_bias_builder-0.1.1.dist-info/top_level.txt
asr_bias_builder-0.1.1.dist-info/RECORD
