Metadata-Version: 2.4
Name: asr-bias-builder
Version: 0.1.1
Summary: Build ASR bias artifacts from presentation decks
Author-email: Yaniv Golan <yaniv@golan.name>
License: MIT
Project-URL: Homepage, https://github.com/yaniv-golan/asr-bias-builder
Project-URL: Documentation, https://github.com/yaniv-golan/asr-bias-builder/tree/main/docs
Classifier: Development Status :: 4 - Beta
Classifier: Intended Audience :: Developers
Classifier: License :: OSI Approved :: MIT License
Classifier: Programming Language :: Python :: 3
Classifier: Programming Language :: Python :: 3.11
Classifier: Programming Language :: Python :: 3.12
Classifier: Programming Language :: Python :: 3.13
Classifier: Topic :: Software Development :: Libraries :: Python Modules
Classifier: Topic :: Multimedia :: Sound/Audio :: Speech
Requires-Python: >=3.11
License-File: LICENSE
Requires-Dist: PyMuPDF>=1.26.6
Requires-Dist: pdfminer.six>=20231228
Requires-Dist: python-pptx>=0.6.23
Requires-Dist: pytesseract>=0.3.10
Requires-Dist: Pillow>=10.2.0
Requires-Dist: PyYAML>=6.0
Requires-Dist: regex>=2023.12
Requires-Dist: flashtext>=2.7
Provides-Extra: google
Requires-Dist: google-cloud-speech>=2.20.0; extra == "google"
Provides-Extra: all
Requires-Dist: spacy>=3.7; extra == "all"
Requires-Dist: google-cloud-speech>=2.20.0; extra == "all"
Requires-Dist: pytesseract>=0.3.10; extra == "all"
Dynamic: license-file
